{"_id":{"$oid":"63fc26e898cb185b745d53e1"},"id":152,"bk_supplier_account":"0","bk_obj_id":"region","bk_property_id":"bk_inst_name","bk_property_name":"实例名","bk_property_group":"default","bk_property_index":0,"unit":"","placeholder":"","editable":true,"ispre":true,"isrequired":true,"isreadonly":false,"isonly":true,"bk_issystem":false,"bk_isapi":false,"bk_property_type":"singlechar","option":null,"description":"","creator":"user","create_time":{"$date":"2023-02-27T03:43:36.299Z"},"last_time":{"$date":"2023-02-27T03:43:36.299Z"},"bk_biz_id":0}
{"_id":{"$oid":"63fc26e898cb185b745d53e2"},"id":158,"bk_supplier_account":"0","bk_obj_id":"region","bk_property_id":"RegionID","bk_property_name":"地域ID","bk_property_group":"default","bk_property_index":1,"unit":"","placeholder":"","editable":true,"ispre":false,"isrequired":false,"isreadonly":false,"isonly":false,"bk_issystem":false,"bk_isapi":false,"bk_property_type":"singlechar","option":null,"description":"","creator":"user","create_time":{"$date":"2023-02-27T03:43:36.299Z"},"last_time":{"$date":"2023-02-27T03:43:36.299Z"},"bk_biz_id":0}
{"_id":{"$oid":"63fc26e898cb185b745d53e3"},"id":159,"bk_supplier_account":"0","bk_obj_id":"region","bk_property_id":"RegionName","bk_property_name":"地域名称","bk_property_group":"default","bk_property_index":2,"unit":"","placeholder":"","editable":true,"ispre":false,"isrequired":false,"isreadonly":false,"isonly":false,"bk_issystem":false,"bk_isapi":false,"bk_property_type":"singlechar","option":null,"description":"","creator":"user","create_time":{"$date":"2023-02-27T03:43:36.299Z"},"last_time":{"$date":"2023-02-27T03:43:36.299Z"},"bk_biz_id":0}
{"_id":{"$oid":"63fc26e898cb185b745d53e4"},"id":160,"bk_supplier_account":"0","bk_obj_id":"region","bk_property_id":"RegionPublicity","bk_property_name":"地域属性","bk_property_group":"default","bk_property_index":3,"unit":"","placeholder":"","editable":true,"ispre":false,"isrequired":true,"isreadonly":false,"isonly":false,"bk_issystem":false,"bk_isapi":false,"bk_property_type":"bool","option":false,"description":"","creator":"user","create_time":{"$date":"2023-02-27T03:43:36.299Z"},"last_time":{"$date":"2023-02-27T03:43:36.299Z"},"bk_biz_id":0}
{"_id":{"$oid":"63fc26e898cb185b745d53e5"},"id":161,"bk_supplier_account":"0","bk_obj_id":"region","bk_property_id":"StackEndpoint","bk_property_name":"stack端点","bk_property_group":"default","bk_property_index":4,"unit":"","placeholder":"","editable":true,"ispre":false,"isrequired":false,"isreadonly":false,"isonly":false,"bk_issystem":false,"bk_isapi":false,"bk_property_type":"singlechar","option":null,"description":"","creator":"user","create_time":{"$date":"2023-02-27T03:43:36.299Z"},"last_time":{"$date":"2023-02-27T03:43:36.299Z"},"bk_biz_id":0}
{"_id":{"$oid":"63fc26e898cb185b745d53e9"},"id":168,"bk_supplier_account":"0","bk_obj_id":"region","bk_property_id":"CreateAt","bk_property_name":"创建时间","bk_property_group":"default","bk_property_index":8,"unit":"","placeholder":"","editable":true,"ispre":false,"isrequired":false,"isreadonly":false,"isonly":false,"bk_issystem":false,"bk_isapi":false,"bk_property_type":"time","option":null,"description":"","creator":"user","create_time":{"$date":"2023-02-27T03:43:36.299Z"},"last_time":{"$date":"2023-02-27T03:43:36.299Z"},"bk_biz_id":0}
{"_id":{"$oid":"63fc26e898cb185b745d53e6"},"id":163,"bk_supplier_account":"0","bk_obj_id":"region","bk_property_id":"Description","bk_property_name":"描述","bk_property_group":"default","bk_property_index":5,"unit":"","placeholder":"","editable":true,"ispre":false,"isrequired":false,"isreadonly":false,"isonly":false,"bk_issystem":false,"bk_isapi":false,"bk_property_type":"longchar","option":null,"description":"","creator":"user","create_time":{"$date":"2023-02-27T03:43:36.299Z"},"last_time":{"$date":"2023-02-27T03:43:36.299Z"},"bk_biz_id":0}
{"_id":{"$oid":"63fc26e898cb185b745d53ea"},"id":169,"bk_supplier_account":"0","bk_obj_id":"region","bk_property_id":"UpdateAt","bk_property_name":"更新时间","bk_property_group":"default","bk_property_index":9,"unit":"","placeholder":"","editable":true,"ispre":false,"isrequired":false,"isreadonly":false,"isonly":false,"bk_issystem":false,"bk_isapi":false,"bk_property_type":"time","option":null,"description":"","creator":"user","create_time":{"$date":"2023-02-27T03:43:36.299Z"},"last_time":{"$date":"2023-02-27T03:43:36.299Z"},"bk_biz_id":0}
{"_id":{"$oid":"63fc26e898cb185b745d53e8"},"id":167,"bk_supplier_account":"0","bk_obj_id":"region","bk_property_id":"Deleted","bk_property_name":"归档标记","bk_property_group":"default","bk_property_index":7,"unit":"","placeholder":"","editable":true,"ispre":false,"isrequired":false,"isreadonly":false,"isonly":false,"bk_issystem":false,"bk_isapi":false,"bk_property_type":"bool","option":false,"description":"","creator":"user","create_time":{"$date":"2023-02-27T03:43:36.299Z"},"last_time":{"$date":"2023-02-27T03:43:36.299Z"},"bk_biz_id":0}
{"_id":{"$oid":"63fc26e898cb185b745d53eb"},"id":170,"bk_supplier_account":"0","bk_obj_id":"region","bk_property_id":"SyncAt","bk_property_name":"同步时间","bk_property_group":"default","bk_property_index":10,"unit":"","placeholder":"","editable":true,"ispre":false,"isrequired":false,"isreadonly":false,"isonly":false,"bk_issystem":false,"bk_isapi":false,"bk_property_type":"time","option":null,"description":"","creator":"user","create_time":{"$date":"2023-02-27T03:43:36.299Z"},"last_time":{"$date":"2023-02-27T03:43:36.299Z"},"bk_biz_id":0}
{"_id":{"$oid":"63fc26e898cb185b745d53ec"},"id":171,"bk_supplier_account":"0","bk_obj_id":"region","bk_property_id":"ZoneNumber","bk_property_name":"可用区数量","bk_property_group":"default","bk_property_index":11,"unit":"","placeholder":"","editable":true,"ispre":false,"isrequired":false,"isreadonly":false,"isonly":false,"bk_issystem":false,"bk_isapi":false,"bk_property_type":"int","option":{"min":"","max":""},"description":"","creator":"user","create_time":{"$date":"2023-02-27T03:43:36.299Z"},"last_time":{"$date":"2023-02-27T03:43:36.299Z"},"bk_biz_id":0}
{"_id":{"$oid":"63fc26e898cb185b745d53ed"},"id":190,"bk_supplier_account":"0","bk_obj_id":"zone","bk_property_id":"bk_inst_name","bk_property_name":"实例名","bk_property_group":"default","bk_property_index":0,"unit":"","placeholder":"","editable":true,"ispre":true,"isrequired":true,"isreadonly":false,"isonly":true,"bk_issystem":false,"bk_isapi":false,"bk_property_type":"singlechar","option":null,"description":"","creator":"user","create_time":{"$date":"2023-02-27T03:43:36.299Z"},"last_time":{"$date":"2023-02-27T03:43:36.299Z"},"bk_biz_id":0}
{"_id":{"$oid":"63fc26e898cb185b745d53ef"},"id":192,"bk_supplier_account":"0","bk_obj_id":"zone","bk_property_id":"RegionName","bk_property_name":"地域名称","bk_property_group":"default","bk_property_index":2,"unit":"","placeholder":"","editable":true,"ispre":false,"isrequired":false,"isreadonly":false,"isonly":false,"bk_issystem":false,"bk_isapi":false,"bk_property_type":"singlechar","option":null,"description":"","creator":"user","create_time":{"$date":"2023-02-27T03:43:36.299Z"},"last_time":{"$date":"2023-02-27T03:43:36.299Z"},"bk_biz_id":0}
{"_id":{"$oid":"63fc26e898cb185b745d53ee"},"id":191,"bk_supplier_account":"0","bk_obj_id":"zone","bk_property_id":"RegionID","bk_property_name":"地域ID","bk_property_group":"default","bk_property_index":1,"unit":"","placeholder":"","editable":true,"ispre":false,"isrequired":false,"isreadonly":false,"isonly":false,"bk_issystem":false,"bk_isapi":false,"bk_property_type":"singlechar","option":null,"description":"","creator":"user","create_time":{"$date":"2023-02-27T03:43:36.299Z"},"last_time":{"$date":"2023-02-27T03:43:36.299Z"},"bk_biz_id":0}
{"_id":{"$oid":"63fc26e898cb185b745d53f1"},"id":194,"bk_supplier_account":"0","bk_obj_id":"zone","bk_property_id":"ZoneName","bk_property_name":"可用区名称","bk_property_group":"default","bk_property_index":4,"unit":"","placeholder":"","editable":true,"ispre":false,"isrequired":false,"isreadonly":false,"isonly":false,"bk_issystem":false,"bk_isapi":false,"bk_property_type":"singlechar","option":null,"description":"","creator":"user","create_time":{"$date":"2023-02-27T03:43:36.299Z"},"last_time":{"$date":"2023-02-27T03:43:36.299Z"},"bk_biz_id":0}
{"_id":{"$oid":"63fc26e898cb185b745d53f0"},"id":193,"bk_supplier_account":"0","bk_obj_id":"zone","bk_property_id":"ZoneID","bk_property_name":"可用区ID","bk_property_group":"default","bk_property_index":3,"unit":"","placeholder":"","editable":true,"ispre":false,"isrequired":false,"isreadonly":false,"isonly":false,"bk_issystem":false,"bk_isapi":false,"bk_property_type":"singlechar","option":null,"description":"","creator":"user","create_time":{"$date":"2023-02-27T03:43:36.299Z"},"last_time":{"$date":"2023-02-27T03:43:36.299Z"},"bk_biz_id":0}
{"_id":{"$oid":"63fc26e898cb185b745d53f2"},"id":195,"bk_supplier_account":"0","bk_obj_id":"zone","bk_property_id":"Description","bk_property_name":"描述","bk_property_group":"default","bk_property_index":5,"unit":"","placeholder":"","editable":true,"ispre":false,"isrequired":false,"isreadonly":false,"isonly":false,"bk_issystem":false,"bk_isapi":false,"bk_property_type":"longchar","option":null,"description":"","creator":"user","create_time":{"$date":"2023-02-27T03:43:36.299Z"},"last_time":{"$date":"2023-02-27T03:43:36.299Z"},"bk_biz_id":0}
{"_id":{"$oid":"63fc26e898cb185b745d53e7"},"id":166,"bk_supplier_account":"0","bk_obj_id":"region","bk_property_id":"RegionState","bk_property_name":"状态","bk_property_group":"default","bk_property_index":6,"unit":"","placeholder":"","editable":true,"ispre":false,"isrequired":false,"isreadonly":false,"isonly":false,"bk_issystem":false,"bk_isapi":false,"bk_property_type":"list","option":["Ready","Enabled","Disabled","Archived"],"description":"","creator":"user","create_time":{"$date":"2023-02-27T03:43:36.299Z"},"last_time":{"$date":"2023-02-27T03:43:36.299Z"},"bk_biz_id":0}
{"_id":{"$oid":"63fc26e898cb185b745d53f4"},"id":197,"bk_supplier_account":"0","bk_obj_id":"zone","bk_property_id":"Deleted","bk_property_name":"归档标记","bk_property_group":"default","bk_property_index":7,"unit":"","placeholder":"","editable":true,"ispre":false,"isrequired":false,"isreadonly":false,"isonly":false,"bk_issystem":false,"bk_isapi":false,"bk_property_type":"bool","option":false,"description":"","creator":"user","create_time":{"$date":"2023-02-27T03:43:36.299Z"},"last_time":{"$date":"2023-02-27T03:43:36.299Z"},"bk_biz_id":0}
{"_id":{"$oid":"63fc26e898cb185b745d5403"},"id":216,"bk_supplier_account":"0","bk_obj_id":"cluster","bk_property_id":"ReservedCpu","bk_property_name":"保留cpu资源","bk_property_group":"default","bk_property_index":6,"unit":"","placeholder":"","editable":true,"ispre":false,"isrequired":false,"isreadonly":false,"isonly":false,"bk_issystem":false,"bk_isapi":false,"bk_property_type":"int","option":{"min":"","max":""},"description":"","creator":"user","create_time":{"$date":"2023-02-27T03:43:36.299Z"},"last_time":{"$date":"2023-02-27T03:43:36.299Z"},"bk_biz_id":0}
{"_id":{"$oid":"63fc26e898cb185b745d53f7"},"id":200,"bk_supplier_account":"0","bk_obj_id":"zone","bk_property_id":"SyncAt","bk_property_name":"同步时间","bk_property_group":"default","bk_property_index":10,"unit":"","placeholder":"","editable":true,"ispre":false,"isrequired":false,"isreadonly":false,"isonly":false,"bk_issystem":false,"bk_isapi":false,"bk_property_type":"time","option":null,"description":"","creator":"user","create_time":{"$date":"2023-02-27T03:43:36.299Z"},"last_time":{"$date":"2023-02-27T03:43:36.299Z"},"bk_biz_id":0}
{"_id":{"$oid":"63fc26e898cb185b745d5405"},"id":218,"bk_supplier_account":"0","bk_obj_id":"cluster","bk_property_id":"CpuRatio","bk_property_name":"cpu超分比","bk_property_group":"default","bk_property_index":8,"unit":"","placeholder":"","editable":true,"ispre":false,"isrequired":false,"isreadonly":false,"isonly":false,"bk_issystem":false,"bk_isapi":false,"bk_property_type":"float","option":{"min":"","max":""},"description":"","creator":"user","create_time":{"$date":"2023-02-27T03:43:36.299Z"},"last_time":{"$date":"2023-02-27T03:43:36.299Z"},"bk_biz_id":0}
{"_id":{"$oid":"63fc26e898cb185b745d5404"},"id":217,"bk_supplier_account":"0","bk_obj_id":"cluster","bk_property_id":"ReservedMemory","bk_property_name":"保留内存资源","bk_property_group":"default","bk_property_index":7,"unit":"","placeholder":"","editable":true,"ispre":false,"isrequired":false,"isreadonly":false,"isonly":false,"bk_issystem":false,"bk_isapi":false,"bk_property_type":"int","option":{"min":"","max":""},"description":"","creator":"user","create_time":{"$date":"2023-02-27T03:43:36.299Z"},"last_time":{"$date":"2023-02-27T03:43:36.299Z"},"bk_biz_id":0}
{"_id":{"$oid":"63fc26e898cb185b745d5406"},"id":219,"bk_supplier_account":"0","bk_obj_id":"cluster","bk_property_id":"MemoryRatio","bk_property_name":"内存超分比","bk_property_group":"default","bk_property_index":9,"unit":"","placeholder":"","editable":true,"ispre":false,"isrequired":false,"isreadonly":false,"isonly":false,"bk_issystem":false,"bk_isapi":false,"bk_property_type":"float","option":{"min":"","max":""},"description":"","creator":"user","create_time":{"$date":"2023-02-27T03:43:36.299Z"},"last_time":{"$date":"2023-02-27T03:43:36.299Z"},"bk_biz_id":0}
{"_id":{"$oid":"63fc26e898cb185b745d5402"},"id":215,"bk_supplier_account":"0","bk_obj_id":"cluster","bk_property_id":"Description","bk_property_name":"集群描述","bk_property_group":"default","bk_property_index":5,"unit":"","placeholder":"","editable":true,"ispre":false,"isrequired":false,"isreadonly":false,"isonly":false,"bk_issystem":false,"bk_isapi":false,"bk_property_type":"longchar","option":null,"description":"","creator":"user","create_time":{"$date":"2023-02-27T03:43:36.299Z"},"last_time":{"$date":"2023-02-27T03:43:36.299Z"},"bk_biz_id":0}
{"_id":{"$oid":"63fc26e898cb185b745d5408"},"id":221,"bk_supplier_account":"0","bk_obj_id":"cluster","bk_property_id":"Deleted","bk_property_name":"归档标记","bk_property_group":"default","bk_property_index":11,"unit":"","placeholder":"","editable":true,"ispre":false,"isrequired":false,"isreadonly":false,"isonly":false,"bk_issystem":false,"bk_isapi":false,"bk_property_type":"bool","option":false,"description":"","creator":"user","create_time":{"$date":"2023-02-27T03:43:36.299Z"},"last_time":{"$date":"2023-02-27T03:43:36.299Z"},"bk_biz_id":0}
{"_id":{"$oid":"63fc26e898cb185b745d5409"},"id":222,"bk_supplier_account":"0","bk_obj_id":"cluster","bk_property_id":"PkID","bk_property_name":"主键","bk_property_group":"default","bk_property_index":12,"unit":"","placeholder":"","editable":true,"ispre":false,"isrequired":false,"isreadonly":false,"isonly":false,"bk_issystem":false,"bk_isapi":false,"bk_property_type":"int","option":{"min":"","max":""},"description":"","creator":"user","create_time":{"$date":"2023-02-27T03:43:36.299Z"},"last_time":{"$date":"2023-02-27T03:43:36.299Z"},"bk_biz_id":0}
{"_id":{"$oid":"63fc26e898cb185b745d53f5"},"id":198,"bk_supplier_account":"0","bk_obj_id":"zone","bk_property_id":"CreateAt","bk_property_name":"创建时间","bk_property_group":"default","bk_property_index":8,"unit":"","placeholder":"","editable":true,"ispre":false,"isrequired":false,"isreadonly":false,"isonly":false,"bk_issystem":false,"bk_isapi":false,"bk_property_type":"time","option":null,"description":"","creator":"user","create_time":{"$date":"2023-02-27T03:43:36.299Z"},"last_time":{"$date":"2023-02-27T03:43:36.299Z"},"bk_biz_id":0}
{"_id":{"$oid":"63fc26e898cb185b745d540c"},"id":225,"bk_supplier_account":"0","bk_obj_id":"cluster","bk_property_id":"CreateAt","bk_property_name":"创建时间","bk_property_group":"default","bk_property_index":15,"unit":"","placeholder":"","editable":true,"ispre":false,"isrequired":false,"isreadonly":false,"isonly":false,"bk_issystem":false,"bk_isapi":false,"bk_property_type":"time","option":null,"description":"","creator":"user","create_time":{"$date":"2023-02-27T03:43:36.299Z"},"last_time":{"$date":"2023-02-27T03:43:36.299Z"},"bk_biz_id":0}
{"_id":{"$oid":"63fc26e898cb185b745d540d"},"id":226,"bk_supplier_account":"0","bk_obj_id":"cluster","bk_property_id":"UpdateAt","bk_property_name":"更新时间","bk_property_group":"default","bk_property_index":16,"unit":"","placeholder":"","editable":true,"ispre":false,"isrequired":false,"isreadonly":false,"isonly":false,"bk_issystem":false,"bk_isapi":false,"bk_property_type":"time","option":null,"description":"","creator":"user","create_time":{"$date":"2023-02-27T03:43:36.299Z"},"last_time":{"$date":"2023-02-27T03:43:36.299Z"},"bk_biz_id":0}
{"_id":{"$oid":"63fc26e898cb185b745d540e"},"id":227,"bk_supplier_account":"0","bk_obj_id":"cluster","bk_property_id":"RegionName","bk_property_name":"地域名称","bk_property_group":"default","bk_property_index":17,"unit":"","placeholder":"","editable":true,"ispre":false,"isrequired":false,"isreadonly":false,"isonly":false,"bk_issystem":false,"bk_isapi":false,"bk_property_type":"singlechar","option":null,"description":"","creator":"user","create_time":{"$date":"2023-02-27T03:43:36.299Z"},"last_time":{"$date":"2023-02-27T03:43:36.299Z"},"bk_biz_id":0}
{"_id":{"$oid":"63fc26e898cb185b745d5410"},"id":250,"bk_supplier_account":"0","bk_obj_id":"storageBackendPool","bk_property_id":"bk_inst_name","bk_property_name":"实例名","bk_property_group":"default","bk_property_index":0,"unit":"","placeholder":"","editable":true,"ispre":true,"isrequired":true,"isreadonly":false,"isonly":true,"bk_issystem":false,"bk_isapi":false,"bk_property_type":"singlechar","option":null,"description":"","creator":"user","create_time":{"$date":"2023-02-27T03:43:36.299Z"},"last_time":{"$date":"2023-02-27T03:43:36.299Z"},"bk_biz_id":0}
{"_id":{"$oid":"63fc26e898cb185b745d540f"},"id":228,"bk_supplier_account":"0","bk_obj_id":"cluster","bk_property_id":"ZoneName","bk_property_name":"可用区名称","bk_property_group":"default","bk_property_index":18,"unit":"","placeholder":"","editable":true,"ispre":false,"isrequired":false,"isreadonly":false,"isonly":false,"bk_issystem":false,"bk_isapi":false,"bk_property_type":"singlechar","option":null,"description":"","creator":"user","create_time":{"$date":"2023-02-27T03:43:36.299Z"},"last_time":{"$date":"2023-02-27T03:43:36.299Z"},"bk_biz_id":0}
{"_id":{"$oid":"63fc26e898cb185b745d5411"},"id":251,"bk_supplier_account":"0","bk_obj_id":"storageBackendPool","bk_property_id":"StorageBackendPoolID","bk_property_name":"存储后端池ID","bk_property_group":"default","bk_property_index":1,"unit":"","placeholder":"","editable":true,"ispre":false,"isrequired":false,"isreadonly":false,"isonly":false,"bk_issystem":false,"bk_isapi":false,"bk_property_type":"singlechar","option":null,"description":"","creator":"user","create_time":{"$date":"2023-02-27T03:43:36.299Z"},"last_time":{"$date":"2023-02-27T03:43:36.299Z"},"bk_biz_id":0}
{"_id":{"$oid":"63fc26e898cb185b745d5413"},"id":253,"bk_supplier_account":"0","bk_obj_id":"storageBackendPool","bk_property_id":"PoolName","bk_property_name":"池名称","bk_property_group":"default","bk_property_index":3,"unit":"","placeholder":"","editable":true,"ispre":false,"isrequired":false,"isreadonly":false,"isonly":false,"bk_issystem":false,"bk_isapi":false,"bk_property_type":"singlechar","option":null,"description":"","creator":"user","create_time":{"$date":"2023-02-27T03:43:36.299Z"},"last_time":{"$date":"2023-02-27T03:43:36.299Z"},"bk_biz_id":0}
{"_id":{"$oid":"63fc26e898cb185b745d5414"},"id":254,"bk_supplier_account":"0","bk_obj_id":"storageBackendPool","bk_property_id":"TotalCapacity","bk_property_name":"池总存储大小","bk_property_group":"default","bk_property_index":4,"unit":"","placeholder":"","editable":true,"ispre":false,"isrequired":false,"isreadonly":false,"isonly":false,"bk_issystem":false,"bk_isapi":false,"bk_property_type":"int","option":{"min":"","max":""},"description":"","creator":"user","create_time":{"$date":"2023-02-27T03:43:36.299Z"},"last_time":{"$date":"2023-02-27T03:43:36.299Z"},"bk_biz_id":0}
{"_id":{"$oid":"63fc26e898cb185b745d5412"},"id":252,"bk_supplier_account":"0","bk_obj_id":"storageBackendPool","bk_property_id":"StorageBackendID","bk_property_name":"存储后端ID","bk_property_group":"default","bk_property_index":2,"unit":"","placeholder":"","editable":true,"ispre":false,"isrequired":false,"isreadonly":false,"isonly":false,"bk_issystem":false,"bk_isapi":false,"bk_property_type":"singlechar","option":null,"description":"","creator":"user","create_time":{"$date":"2023-02-27T03:43:36.299Z"},"last_time":{"$date":"2023-02-27T03:43:36.299Z"},"bk_biz_id":0}
{"_id":{"$oid":"63fc26e898cb185b745d5415"},"id":255,"bk_supplier_account":"0","bk_obj_id":"storageBackendPool","bk_property_id":"CreateAt","bk_property_name":"创建时间","bk_property_group":"default","bk_property_index":5,"unit":"","placeholder":"","editable":true,"ispre":false,"isrequired":false,"isreadonly":false,"isonly":false,"bk_issystem":false,"bk_isapi":false,"bk_property_type":"time","option":null,"description":"","creator":"user","create_time":{"$date":"2023-02-27T03:43:36.299Z"},"last_time":{"$date":"2023-02-27T03:43:36.299Z"},"bk_biz_id":0}
{"_id":{"$oid":"63fc26e898cb185b745d5416"},"id":256,"bk_supplier_account":"0","bk_obj_id":"storageBackendPool","bk_property_id":"UpdateAt","bk_property_name":"更新时间","bk_property_group":"default","bk_property_index":6,"unit":"","placeholder":"","editable":true,"ispre":false,"isrequired":false,"isreadonly":false,"isonly":false,"bk_issystem":false,"bk_isapi":false,"bk_property_type":"time","option":null,"description":"","creator":"user","create_time":{"$date":"2023-02-27T03:43:36.299Z"},"last_time":{"$date":"2023-02-27T03:43:36.299Z"},"bk_biz_id":0}
{"_id":{"$oid":"63fc26e898cb185b745d53f8"},"id":201,"bk_supplier_account":"0","bk_obj_id":"zone","bk_property_id":"ReservedCpu","bk_property_name":"保留cpu资源","bk_property_group":"default","bk_property_index":11,"unit":"","placeholder":"","editable":true,"ispre":false,"isrequired":false,"isreadonly":false,"isonly":false,"bk_issystem":false,"bk_isapi":false,"bk_property_type":"int","option":{"min":"","max":""},"description":"","creator":"user","create_time":{"$date":"2023-02-27T03:43:36.299Z"},"last_time":{"$date":"2023-02-27T03:43:36.299Z"},"bk_biz_id":0}
{"_id":{"$oid":"63fc26e898cb185b745d53f6"},"id":199,"bk_supplier_account":"0","bk_obj_id":"zone","bk_property_id":"UpdateAt","bk_property_name":"更新时间","bk_property_group":"default","bk_property_index":9,"unit":"","placeholder":"","editable":true,"ispre":false,"isrequired":false,"isreadonly":false,"isonly":false,"bk_issystem":false,"bk_isapi":false,"bk_property_type":"time","option":null,"description":"","creator":"user","create_time":{"$date":"2023-02-27T03:43:36.299Z"},"last_time":{"$date":"2023-02-27T03:43:36.299Z"},"bk_biz_id":0}
{"_id":{"$oid":"63fc26e898cb185b745d53f3"},"id":196,"bk_supplier_account":"0","bk_obj_id":"zone","bk_property_id":"ZoneState","bk_property_name":"状态","bk_property_group":"default","bk_property_index":6,"unit":"","placeholder":"","editable":true,"ispre":false,"isrequired":false,"isreadonly":false,"isonly":false,"bk_issystem":false,"bk_isapi":false,"bk_property_type":"list","option":["Ready","Enabled","Disabled","Archived"],"description":"","creator":"user","create_time":{"$date":"2023-02-27T03:43:36.299Z"},"last_time":{"$date":"2023-02-27T03:43:36.299Z"},"bk_biz_id":0}
{"_id":{"$oid":"63fc26e898cb185b745d53fd"},"id":210,"bk_supplier_account":"0","bk_obj_id":"cluster","bk_property_id":"bk_inst_name","bk_property_name":"实例名","bk_property_group":"default","bk_property_index":0,"unit":"","placeholder":"","editable":true,"ispre":true,"isrequired":true,"isreadonly":false,"isonly":true,"bk_issystem":false,"bk_isapi":false,"bk_property_type":"singlechar","option":null,"description":"","creator":"user","create_time":{"$date":"2023-02-27T03:43:36.299Z"},"last_time":{"$date":"2023-02-27T03:43:36.299Z"},"bk_biz_id":0}
{"_id":{"$oid":"63fc26e898cb185b745d53fe"},"id":211,"bk_supplier_account":"0","bk_obj_id":"cluster","bk_property_id":"RegionID","bk_property_name":"地域ID","bk_property_group":"default","bk_property_index":1,"unit":"","placeholder":"","editable":true,"ispre":false,"isrequired":false,"isreadonly":false,"isonly":false,"bk_issystem":false,"bk_isapi":false,"bk_property_type":"singlechar","option":null,"description":"","creator":"user","create_time":{"$date":"2023-02-27T03:43:36.299Z"},"last_time":{"$date":"2023-02-27T03:43:36.299Z"},"bk_biz_id":0}
{"_id":{"$oid":"63fc26e898cb185b745d5407"},"id":220,"bk_supplier_account":"0","bk_obj_id":"cluster","bk_property_id":"State","bk_property_name":"集群状态","bk_property_group":"default","bk_property_index":10,"unit":"","placeholder":"","editable":true,"ispre":false,"isrequired":false,"isreadonly":false,"isonly":false,"bk_issystem":false,"bk_isapi":false,"bk_property_type":"list","option":["Ready","Enabled","Disabled","Archived"],"description":"","creator":"user","create_time":{"$date":"2023-02-27T03:43:36.299Z"},"last_time":{"$date":"2023-02-27T03:43:36.299Z"},"bk_biz_id":0}
{"_id":{"$oid":"63fc26e898cb185b745d541e"},"id":277,"bk_supplier_account":"0","bk_obj_id":"storageBackend","bk_property_id":"Password","bk_property_name":"密码","bk_property_group":"default","bk_property_index":7,"unit":"","placeholder":"","editable":true,"ispre":false,"isrequired":false,"isreadonly":false,"isonly":false,"bk_issystem":false,"bk_isapi":false,"bk_property_type":"singlechar","option":null,"description":"","creator":"user","create_time":{"$date":"2023-02-27T03:43:36.299Z"},"last_time":{"$date":"2023-02-27T03:43:36.299Z"},"bk_biz_id":0}
{"_id":{"$oid":"63fc26e898cb185b745d541f"},"id":278,"bk_supplier_account":"0","bk_obj_id":"storageBackend","bk_property_id":"CreateAt","bk_property_name":"创建时间","bk_property_group":"default","bk_property_index":8,"unit":"","placeholder":"","editable":true,"ispre":false,"isrequired":false,"isreadonly":false,"isonly":false,"bk_issystem":false,"bk_isapi":false,"bk_property_type":"time","option":null,"description":"","creator":"user","create_time":{"$date":"2023-02-27T03:43:36.299Z"},"last_time":{"$date":"2023-02-27T03:43:36.299Z"},"bk_biz_id":0}
{"_id":{"$oid":"63fc26e898cb185b745d541d"},"id":276,"bk_supplier_account":"0","bk_obj_id":"storageBackend","bk_property_id":"Username","bk_property_name":"用户名","bk_property_group":"default","bk_property_index":6,"unit":"","placeholder":"","editable":true,"ispre":false,"isrequired":false,"isreadonly":false,"isonly":false,"bk_issystem":false,"bk_isapi":false,"bk_property_type":"singlechar","option":null,"description":"","creator":"user","create_time":{"$date":"2023-02-27T03:43:36.299Z"},"last_time":{"$date":"2023-02-27T03:43:36.299Z"},"bk_biz_id":0}
{"_id":{"$oid":"63fc26e898cb185b745d541c"},"id":275,"bk_supplier_account":"0","bk_obj_id":"storageBackend","bk_property_id":"Url","bk_property_name":"存储后端url","bk_property_group":"default","bk_property_index":5,"unit":"","placeholder":"","editable":true,"ispre":false,"isrequired":false,"isreadonly":false,"isonly":false,"bk_issystem":false,"bk_isapi":false,"bk_property_type":"singlechar","option":null,"description":"","creator":"user","create_time":{"$date":"2023-02-27T03:43:36.299Z"},"last_time":{"$date":"2023-02-27T03:43:36.299Z"},"bk_biz_id":0}
{"_id":{"$oid":"63fc26e898cb185b745d5421"},"id":300,"bk_supplier_account":"0","bk_obj_id":"cmdb_host","bk_property_id":"bk_inst_name","bk_property_name":"实例名","bk_property_group":"default","bk_property_index":0,"unit":"","placeholder":"","editable":true,"ispre":true,"isrequired":true,"isreadonly":false,"isonly":true,"bk_issystem":false,"bk_isapi":false,"bk_property_type":"singlechar","option":null,"description":"","creator":"user","create_time":{"$date":"2023-02-27T03:43:36.299Z"},"last_time":{"$date":"2023-02-27T03:43:36.299Z"},"bk_biz_id":0}
{"_id":{"$oid":"63fc26e898cb185b745d5422"},"id":301,"bk_supplier_account":"0","bk_obj_id":"cmdb_host","bk_property_id":"HostID","bk_property_name":"主机ID","bk_property_group":"default","bk_property_index":1,"unit":"","placeholder":"","editable":true,"ispre":false,"isrequired":false,"isreadonly":false,"isonly":false,"bk_issystem":false,"bk_isapi":false,"bk_property_type":"singlechar","option":null,"description":"","creator":"user","create_time":{"$date":"2023-02-27T03:43:36.299Z"},"last_time":{"$date":"2023-02-27T03:43:36.299Z"},"bk_biz_id":0}
{"_id":{"$oid":"63fc26e898cb185b745d5420"},"id":279,"bk_supplier_account":"0","bk_obj_id":"storageBackend","bk_property_id":"UpdateAt","bk_property_name":"更新时间","bk_property_group":"default","bk_property_index":9,"unit":"","placeholder":"","editable":true,"ispre":false,"isrequired":false,"isreadonly":false,"isonly":false,"bk_issystem":false,"bk_isapi":false,"bk_property_type":"time","option":null,"description":"","creator":"user","create_time":{"$date":"2023-02-27T03:43:36.299Z"},"last_time":{"$date":"2023-02-27T03:43:36.299Z"},"bk_biz_id":0}
{"_id":{"$oid":"63fc26e898cb185b745d5424"},"id":303,"bk_supplier_account":"0","bk_obj_id":"cmdb_host","bk_property_id":"RegionID","bk_property_name":"地域ID","bk_property_group":"default","bk_property_index":3,"unit":"","placeholder":"","editable":true,"ispre":false,"isrequired":false,"isreadonly":false,"isonly":false,"bk_issystem":false,"bk_isapi":false,"bk_property_type":"singlechar","option":null,"description":"","creator":"user","create_time":{"$date":"2023-02-27T03:43:36.299Z"},"last_time":{"$date":"2023-02-27T03:43:36.299Z"},"bk_biz_id":0}
{"_id":{"$oid":"63fc26e898cb185b745d5423"},"id":302,"bk_supplier_account":"0","bk_obj_id":"cmdb_host","bk_property_id":"HostName","bk_property_name":"主机名称","bk_property_group":"default","bk_property_index":2,"unit":"","placeholder":"","editable":true,"ispre":false,"isrequired":false,"isreadonly":false,"isonly":false,"bk_issystem":false,"bk_isapi":false,"bk_property_type":"singlechar","option":null,"description":"","creator":"user","create_time":{"$date":"2023-02-27T03:43:36.299Z"},"last_time":{"$date":"2023-02-27T03:43:36.299Z"},"bk_biz_id":0}
{"_id":{"$oid":"63fc26e898cb185b745d5425"},"id":304,"bk_supplier_account":"0","bk_obj_id":"cmdb_host","bk_property_id":"ZoneID","bk_property_name":"可用区ID","bk_property_group":"default","bk_property_index":4,"unit":"","placeholder":"","editable":true,"ispre":false,"isrequired":false,"isreadonly":false,"isonly":false,"bk_issystem":false,"bk_isapi":false,"bk_property_type":"singlechar","option":null,"description":"","creator":"user","create_time":{"$date":"2023-02-27T03:43:36.299Z"},"last_time":{"$date":"2023-02-27T03:43:36.299Z"},"bk_biz_id":0}
{"_id":{"$oid":"63fc26e898cb185b745d5426"},"id":305,"bk_supplier_account":"0","bk_obj_id":"cmdb_host","bk_property_id":"ClusterID","bk_property_name":"集群ID","bk_property_group":"default","bk_property_index":5,"unit":"","placeholder":"","editable":true,"ispre":false,"isrequired":false,"isreadonly":false,"isonly":false,"bk_issystem":false,"bk_isapi":false,"bk_property_type":"singlechar","option":null,"description":"","creator":"user","create_time":{"$date":"2023-02-27T03:43:36.299Z"},"last_time":{"$date":"2023-02-27T03:43:36.299Z"},"bk_biz_id":0}
{"_id":{"$oid":"63fc26e898cb185b745d5427"},"id":306,"bk_supplier_account":"0","bk_obj_id":"cmdb_host","bk_property_id":"Description","bk_property_name":"描述","bk_property_group":"default","bk_property_index":6,"unit":"","placeholder":"","editable":true,"ispre":false,"isrequired":false,"isreadonly":false,"isonly":false,"bk_issystem":false,"bk_isapi":false,"bk_property_type":"longchar","option":null,"description":"","creator":"user","create_time":{"$date":"2023-02-27T03:43:36.299Z"},"last_time":{"$date":"2023-02-27T03:43:36.299Z"},"bk_biz_id":0}
{"_id":{"$oid":"63fc26e898cb185b745d5428"},"id":307,"bk_supplier_account":"0","bk_obj_id":"cmdb_host","bk_property_id":"HypervisorType","bk_property_name":"虚拟化类型","bk_property_group":"default","bk_property_index":7,"unit":"","placeholder":"","editable":true,"ispre":false,"isrequired":false,"isreadonly":false,"isonly":false,"bk_issystem":false,"bk_isapi":false,"bk_property_type":"singlechar","option":null,"description":"","creator":"user","create_time":{"$date":"2023-02-27T03:43:36.299Z"},"last_time":{"$date":"2023-02-27T03:43:36.299Z"},"bk_biz_id":0}
{"_id":{"$oid":"63fc26e898cb185b745d5429"},"id":308,"bk_supplier_account":"0","bk_obj_id":"cmdb_host","bk_property_id":"State","bk_property_name":"可用状态","bk_property_group":"default","bk_property_index":8,"unit":"","placeholder":"","editable":true,"ispre":false,"isrequired":false,"isreadonly":false,"isonly":false,"bk_issystem":false,"bk_isapi":false,"bk_property_type":"list","option":["Enabled","Disabled","PreMaintenance","Maintenance"],"description":"","creator":"user","create_time":{"$date":"2023-02-27T03:43:36.299Z"},"last_time":{"$date":"2023-02-27T03:43:36.299Z"},"bk_biz_id":0}
{"_id":{"$oid":"63fc26e898cb185b745d542b"},"id":310,"bk_supplier_account":"0","bk_obj_id":"cmdb_host","bk_property_id":"ReservedCpu","bk_property_name":"保留cpu资源","bk_property_group":"default","bk_property_index":10,"unit":"","placeholder":"","editable":true,"ispre":false,"isrequired":false,"isreadonly":false,"isonly":false,"bk_issystem":false,"bk_isapi":false,"bk_property_type":"int","option":{"min":"","max":""},"description":"","creator":"user","create_time":{"$date":"2023-02-27T03:43:36.299Z"},"last_time":{"$date":"2023-02-27T03:43:36.299Z"},"bk_biz_id":0}
{"_id":{"$oid":"63fc26e898cb185b745d542a"},"id":309,"bk_supplier_account":"0","bk_obj_id":"cmdb_host","bk_property_id":"Status","bk_property_name":"连接状态","bk_property_group":"default","bk_property_index":9,"unit":"","placeholder":"","editable":true,"ispre":false,"isrequired":false,"isreadonly":false,"isonly":false,"bk_issystem":false,"bk_isapi":false,"bk_property_type":"list","option":["Connecting","Connected","Disconnected"],"description":"","creator":"user","create_time":{"$date":"2023-02-27T03:43:36.299Z"},"last_time":{"$date":"2023-02-27T03:43:36.299Z"},"bk_biz_id":0}
{"_id":{"$oid":"63fc26e898cb185b745d542c"},"id":311,"bk_supplier_account":"0","bk_obj_id":"cmdb_host","bk_property_id":"ReservedMemory","bk_property_name":"保留内存资源","bk_property_group":"default","bk_property_index":11,"unit":"","placeholder":"","editable":true,"ispre":false,"isrequired":false,"isreadonly":false,"isonly":false,"bk_issystem":false,"bk_isapi":false,"bk_property_type":"int","option":{"min":"","max":""},"description":"","creator":"user","create_time":{"$date":"2023-02-27T03:43:36.299Z"},"last_time":{"$date":"2023-02-27T03:43:36.299Z"},"bk_biz_id":0}
{"_id":{"$oid":"63fc26e898cb185b745d542d"},"id":312,"bk_supplier_account":"0","bk_obj_id":"cmdb_host","bk_property_id":"CpuRatio","bk_property_name":"Cpu超分比","bk_property_group":"default","bk_property_index":12,"unit":"","placeholder":"","editable":true,"ispre":false,"isrequired":false,"isreadonly":false,"isonly":false,"bk_issystem":false,"bk_isapi":false,"bk_property_type":"float","option":{"max":"","min":""},"description":"","creator":"user","create_time":{"$date":"2023-02-27T03:43:36.299Z"},"last_time":{"$date":"2023-04-13T02:04:05.868Z"},"bk_biz_id":0}
{"_id":{"$oid":"63fc26e898cb185b745d5417"},"id":270,"bk_supplier_account":"0","bk_obj_id":"storageBackend","bk_property_id":"bk_inst_name","bk_property_name":"实例名","bk_property_group":"default","bk_property_index":0,"unit":"","placeholder":"","editable":true,"ispre":true,"isrequired":true,"isreadonly":false,"isonly":true,"bk_issystem":false,"bk_isapi":false,"bk_property_type":"singlechar","option":null,"description":"","creator":"user","create_time":{"$date":"2023-02-27T03:43:36.299Z"},"last_time":{"$date":"2023-02-27T03:43:36.299Z"},"bk_biz_id":0}
{"_id":{"$oid":"63fc26e898cb185b745d53ff"},"id":212,"bk_supplier_account":"0","bk_obj_id":"cluster","bk_property_id":"ZoneID","bk_property_name":"可用区ID","bk_property_group":"default","bk_property_index":2,"unit":"","placeholder":"","editable":true,"ispre":false,"isrequired":false,"isreadonly":false,"isonly":false,"bk_issystem":false,"bk_isapi":false,"bk_property_type":"singlechar","option":null,"description":"","creator":"user","create_time":{"$date":"2023-02-27T03:43:36.299Z"},"last_time":{"$date":"2023-02-27T03:43:36.299Z"},"bk_biz_id":0}
{"_id":{"$oid":"63fc26e898cb185b745d5400"},"id":213,"bk_supplier_account":"0","bk_obj_id":"cluster","bk_property_id":"ClusterID","bk_property_name":"集群ID","bk_property_group":"default","bk_property_index":3,"unit":"","placeholder":"","editable":true,"ispre":false,"isrequired":false,"isreadonly":false,"isonly":false,"bk_issystem":false,"bk_isapi":false,"bk_property_type":"singlechar","option":null,"description":"","creator":"user","create_time":{"$date":"2023-02-27T03:43:36.299Z"},"last_time":{"$date":"2023-02-27T03:43:36.299Z"},"bk_biz_id":0}
{"_id":{"$oid":"63fc26e898cb185b745d5418"},"id":271,"bk_supplier_account":"0","bk_obj_id":"storageBackend","bk_property_id":"StorageBackendID","bk_property_name":"存储后端ID","bk_property_group":"default","bk_property_index":1,"unit":"","placeholder":"","editable":true,"ispre":false,"isrequired":false,"isreadonly":false,"isonly":false,"bk_issystem":false,"bk_isapi":false,"bk_property_type":"singlechar","option":null,"description":"","creator":"user","create_time":{"$date":"2023-02-27T03:43:36.299Z"},"last_time":{"$date":"2023-02-27T03:43:36.299Z"},"bk_biz_id":0}
{"_id":{"$oid":"63fc26e898cb185b745d5401"},"id":214,"bk_supplier_account":"0","bk_obj_id":"cluster","bk_property_id":"ClusterName","bk_property_name":"集群名称","bk_property_group":"default","bk_property_index":4,"unit":"","placeholder":"","editable":true,"ispre":false,"isrequired":false,"isreadonly":false,"isonly":false,"bk_issystem":false,"bk_isapi":false,"bk_property_type":"singlechar","option":null,"description":"","creator":"user","create_time":{"$date":"2023-02-27T03:43:36.299Z"},"last_time":{"$date":"2023-02-27T03:43:36.299Z"},"bk_biz_id":0}
{"_id":{"$oid":"63fc26e898cb185b745d541a"},"id":273,"bk_supplier_account":"0","bk_obj_id":"storageBackend","bk_property_id":"ProtocolType","bk_property_name":"协议类型","bk_property_group":"default","bk_property_index":3,"unit":"","placeholder":"","editable":true,"ispre":false,"isrequired":false,"isreadonly":false,"isonly":false,"bk_issystem":false,"bk_isapi":false,"bk_property_type":"singlechar","option":null,"description":"","creator":"user","create_time":{"$date":"2023-02-27T03:43:36.299Z"},"last_time":{"$date":"2023-02-27T03:43:36.299Z"},"bk_biz_id":0}
{"_id":{"$oid":"63fc26e898cb185b745d542f"},"id":314,"bk_supplier_account":"0","bk_obj_id":"cmdb_host","bk_property_id":"ManagementIp","bk_property_name":"管理网卡ip","bk_property_group":"default","bk_property_index":14,"unit":"","placeholder":"","editable":true,"ispre":false,"isrequired":false,"isreadonly":false,"isonly":false,"bk_issystem":false,"bk_isapi":false,"bk_property_type":"singlechar","option":null,"description":"","creator":"user","create_time":{"$date":"2023-02-27T03:43:36.299Z"},"last_time":{"$date":"2023-02-27T03:43:36.299Z"},"bk_biz_id":0}
{"_id":{"$oid":"63fc26e898cb185b745d542e"},"id":313,"bk_supplier_account":"0","bk_obj_id":"cmdb_host","bk_property_id":"MemoryRatio","bk_property_name":"内存超分比","bk_property_group":"default","bk_property_index":13,"unit":"","placeholder":"","editable":true,"ispre":false,"isrequired":false,"isreadonly":false,"isonly":false,"bk_issystem":false,"bk_isapi":false,"bk_property_type":"float","option":{"min":"","max":""},"description":"","creator":"user","create_time":{"$date":"2023-02-27T03:43:36.299Z"},"last_time":{"$date":"2023-02-27T03:43:36.299Z"},"bk_biz_id":0}
{"_id":{"$oid":"63fc26e898cb185b745d5430"},"id":315,"bk_supplier_account":"0","bk_obj_id":"cmdb_host","bk_property_id":"ManagementMac","bk_property_name":"管理网卡mac地址","bk_property_group":"default","bk_property_index":15,"unit":"","placeholder":"","editable":true,"ispre":false,"isrequired":false,"isreadonly":false,"isonly":false,"bk_issystem":false,"bk_isapi":false,"bk_property_type":"singlechar","option":null,"description":"","creator":"user","create_time":{"$date":"2023-02-27T03:43:36.299Z"},"last_time":{"$date":"2023-02-27T03:43:36.299Z"},"bk_biz_id":0}
{"_id":{"$oid":"63fc26e898cb185b745d5432"},"id":317,"bk_supplier_account":"0","bk_obj_id":"cmdb_host","bk_property_id":"BusinessMac","bk_property_name":"业务网卡mac地址","bk_property_group":"default","bk_property_index":17,"unit":"","placeholder":"","editable":true,"ispre":false,"isrequired":false,"isreadonly":false,"isonly":false,"bk_issystem":false,"bk_isapi":false,"bk_property_type":"singlechar","option":null,"description":"","creator":"user","create_time":{"$date":"2023-02-27T03:43:36.299Z"},"last_time":{"$date":"2023-02-27T03:43:36.299Z"},"bk_biz_id":0}
{"_id":{"$oid":"63fc26e898cb185b745d5433"},"id":318,"bk_supplier_account":"0","bk_obj_id":"cmdb_host","bk_property_id":"StorageIp","bk_property_name":"存储网卡ip","bk_property_group":"default","bk_property_index":18,"unit":"","placeholder":"","editable":true,"ispre":false,"isrequired":false,"isreadonly":false,"isonly":false,"bk_issystem":false,"bk_isapi":false,"bk_property_type":"singlechar","option":null,"description":"","creator":"user","create_time":{"$date":"2023-02-27T03:43:36.299Z"},"last_time":{"$date":"2023-02-27T03:43:36.299Z"},"bk_biz_id":0}
{"_id":{"$oid":"63fc26e898cb185b745d5431"},"id":316,"bk_supplier_account":"0","bk_obj_id":"cmdb_host","bk_property_id":"BusinessIp","bk_property_name":"业务网卡ip","bk_property_group":"default","bk_property_index":16,"unit":"","placeholder":"","editable":true,"ispre":false,"isrequired":false,"isreadonly":false,"isonly":false,"bk_issystem":false,"bk_isapi":false,"bk_property_type":"singlechar","option":null,"description":"","creator":"user","create_time":{"$date":"2023-02-27T03:43:36.299Z"},"last_time":{"$date":"2023-02-27T03:43:36.299Z"},"bk_biz_id":0}
{"_id":{"$oid":"63fc26e898cb185b745d5434"},"id":319,"bk_supplier_account":"0","bk_obj_id":"cmdb_host","bk_property_id":"StorageMac","bk_property_name":"存储网卡mac地址","bk_property_group":"default","bk_property_index":19,"unit":"","placeholder":"","editable":true,"ispre":false,"isrequired":false,"isreadonly":false,"isonly":false,"bk_issystem":false,"bk_isapi":false,"bk_property_type":"singlechar","option":null,"description":"","creator":"user","create_time":{"$date":"2023-02-27T03:43:36.299Z"},"last_time":{"$date":"2023-02-27T03:43:36.299Z"},"bk_biz_id":0}
{"_id":{"$oid":"63fc26e898cb185b745d5435"},"id":320,"bk_supplier_account":"0","bk_obj_id":"cmdb_host","bk_property_id":"Sn","bk_property_name":"序列号","bk_property_group":"default","bk_property_index":20,"unit":"","placeholder":"","editable":true,"ispre":false,"isrequired":false,"isreadonly":false,"isonly":false,"bk_issystem":false,"bk_isapi":false,"bk_property_type":"singlechar","option":null,"description":"","creator":"user","create_time":{"$date":"2023-02-27T03:43:36.299Z"},"last_time":{"$date":"2023-02-27T03:43:36.299Z"},"bk_biz_id":0}
{"_id":{"$oid":"63fc26e898cb185b745d5438"},"id":323,"bk_supplier_account":"0","bk_obj_id":"cmdb_host","bk_property_id":"TotalMemory","bk_property_name":"TotalMemory","bk_property_group":"default","bk_property_index":23,"unit":"","placeholder":"","editable":true,"ispre":false,"isrequired":false,"isreadonly":false,"isonly":false,"bk_issystem":false,"bk_isapi":false,"bk_property_type":"int","option":{"min":"","max":""},"description":"","creator":"user","create_time":{"$date":"2023-02-27T03:43:36.299Z"},"last_time":{"$date":"2023-02-27T03:43:36.299Z"},"bk_biz_id":0}
{"_id":{"$oid":"63fc26e898cb185b745d5437"},"id":322,"bk_supplier_account":"0","bk_obj_id":"cmdb_host","bk_property_id":"TotalCpu","bk_property_name":"TotalCpu","bk_property_group":"default","bk_property_index":22,"unit":"","placeholder":"","editable":true,"ispre":false,"isrequired":false,"isreadonly":false,"isonly":false,"bk_issystem":false,"bk_isapi":false,"bk_property_type":"int","option":{"min":"","max":""},"description":"","creator":"user","create_time":{"$date":"2023-02-27T03:43:36.299Z"},"last_time":{"$date":"2023-02-27T03:43:36.299Z"},"bk_biz_id":0}
{"_id":{"$oid":"63fc26e898cb185b745d5436"},"id":321,"bk_supplier_account":"0","bk_obj_id":"cmdb_host","bk_property_id":"AgentUrl","bk_property_name":"调用agent的url","bk_property_group":"default","bk_property_index":21,"unit":"","placeholder":"","editable":true,"ispre":false,"isrequired":false,"isreadonly":false,"isonly":false,"bk_issystem":false,"bk_isapi":false,"bk_property_type":"singlechar","option":null,"description":"","creator":"user","create_time":{"$date":"2023-02-27T03:43:36.299Z"},"last_time":{"$date":"2023-02-27T03:43:36.299Z"},"bk_biz_id":0}
{"_id":{"$oid":"63fc26e898cb185b745d53fc"},"id":205,"bk_supplier_account":"0","bk_obj_id":"zone","bk_property_id":"MemoryRatio","bk_property_name":"内存超分比","bk_property_group":"default","bk_property_index":15,"unit":"","placeholder":"","editable":true,"ispre":false,"isrequired":false,"isreadonly":false,"isonly":false,"bk_issystem":false,"bk_isapi":false,"bk_property_type":"float","option":{"min":"","max":""},"description":"","creator":"user","create_time":{"$date":"2023-02-27T03:43:36.299Z"},"last_time":{"$date":"2023-02-27T03:43:36.299Z"},"bk_biz_id":0}
{"_id":{"$oid":"63fc26e898cb185b745d5419"},"id":272,"bk_supplier_account":"0","bk_obj_id":"storageBackend","bk_property_id":"StorageType","bk_property_name":"存储类型","bk_property_group":"default","bk_property_index":2,"unit":"","placeholder":"","editable":true,"ispre":false,"isrequired":false,"isreadonly":false,"isonly":false,"bk_issystem":false,"bk_isapi":false,"bk_property_type":"singlechar","option":null,"description":"","creator":"user","create_time":{"$date":"2023-02-27T03:43:36.299Z"},"last_time":{"$date":"2023-02-27T03:43:36.299Z"},"bk_biz_id":0}
{"_id":{"$oid":"63fc26e898cb185b745d543b"},"id":326,"bk_supplier_account":"0","bk_obj_id":"cmdb_host","bk_property_id":"CreateAt","bk_property_name":"创建时间","bk_property_group":"default","bk_property_index":26,"unit":"","placeholder":"","editable":true,"ispre":false,"isrequired":false,"isreadonly":false,"isonly":false,"bk_issystem":false,"bk_isapi":false,"bk_property_type":"time","option":null,"description":"","creator":"user","create_time":{"$date":"2023-02-27T03:43:36.299Z"},"last_time":{"$date":"2023-02-27T03:43:36.299Z"},"bk_biz_id":0}
{"_id":{"$oid":"63fc26e898cb185b745d53f9"},"id":202,"bk_supplier_account":"0","bk_obj_id":"zone","bk_property_id":"ReservedMemory","bk_property_name":"保留内存资源","bk_property_group":"default","bk_property_index":12,"unit":"","placeholder":"","editable":true,"ispre":false,"isrequired":false,"isreadonly":false,"isonly":false,"bk_issystem":false,"bk_isapi":false,"bk_property_type":"int","option":{"min":"","max":""},"description":"","creator":"user","create_time":{"$date":"2023-02-27T03:43:36.299Z"},"last_time":{"$date":"2023-02-27T03:43:36.299Z"},"bk_biz_id":0}
{"_id":{"$oid":"63fc26e898cb185b745d53fb"},"id":204,"bk_supplier_account":"0","bk_obj_id":"zone","bk_property_id":"CpuRatio","bk_property_name":"cpu超分比","bk_property_group":"default","bk_property_index":14,"unit":"","placeholder":"","editable":true,"ispre":false,"isrequired":false,"isreadonly":false,"isonly":false,"bk_issystem":false,"bk_isapi":false,"bk_property_type":"float","option":{"min":"","max":""},"description":"","creator":"user","create_time":{"$date":"2023-02-27T03:43:36.299Z"},"last_time":{"$date":"2023-02-27T03:43:36.299Z"},"bk_biz_id":0}
{"_id":{"$oid":"63fc26e898cb185b745d543c"},"id":327,"bk_supplier_account":"0","bk_obj_id":"cmdb_host","bk_property_id":"UpdateAt","bk_property_name":"更新时间","bk_property_group":"default","bk_property_index":27,"unit":"","placeholder":"","editable":true,"ispre":false,"isrequired":false,"isreadonly":false,"isonly":false,"bk_issystem":false,"bk_isapi":false,"bk_property_type":"time","option":null,"description":"","creator":"user","create_time":{"$date":"2023-02-27T03:43:36.299Z"},"last_time":{"$date":"2023-02-27T03:43:36.299Z"},"bk_biz_id":0}
{"_id":{"$oid":"63fc26e898cb185b745d543a"},"id":325,"bk_supplier_account":"0","bk_obj_id":"cmdb_host","bk_property_id":"TotalExtendResource","bk_property_name":"TotalExtendResource","bk_property_group":"default","bk_property_index":25,"unit":"","placeholder":"","editable":true,"ispre":false,"isrequired":false,"isreadonly":false,"isonly":false,"bk_issystem":false,"bk_isapi":false,"bk_property_type":"singlechar","option":null,"description":"","creator":"user","create_time":{"$date":"2023-02-27T03:43:36.299Z"},"last_time":{"$date":"2023-02-27T03:43:36.299Z"},"bk_biz_id":0}
{"_id":{"$oid":"63fc26e898cb185b745d543e"},"id":329,"bk_supplier_account":"0","bk_obj_id":"cmdb_host","bk_property_id":"ZoneName","bk_property_name":"可用区名称","bk_property_group":"default","bk_property_index":29,"unit":"","placeholder":"","editable":true,"ispre":false,"isrequired":false,"isreadonly":false,"isonly":false,"bk_issystem":false,"bk_isapi":false,"bk_property_type":"singlechar","option":null,"description":"","creator":"user","create_time":{"$date":"2023-02-27T03:43:36.299Z"},"last_time":{"$date":"2023-02-27T03:43:36.299Z"},"bk_biz_id":0}
{"_id":{"$oid":"63fc26e898cb185b745d543d"},"id":328,"bk_supplier_account":"0","bk_obj_id":"cmdb_host","bk_property_id":"RegionName","bk_property_name":"地域名称","bk_property_group":"default","bk_property_index":28,"unit":"","placeholder":"","editable":true,"ispre":false,"isrequired":false,"isreadonly":false,"isonly":false,"bk_issystem":false,"bk_isapi":false,"bk_property_type":"singlechar","option":null,"description":"","creator":"user","create_time":{"$date":"2023-02-27T03:43:36.299Z"},"last_time":{"$date":"2023-02-27T03:43:36.299Z"},"bk_biz_id":0}
{"_id":{"$oid":"63fc26e898cb185b745d5439"},"id":324,"bk_supplier_account":"0","bk_obj_id":"cmdb_host","bk_property_id":"Maintenance","bk_property_name":"Maintenance","bk_property_group":"default","bk_property_index":24,"unit":"","placeholder":"","editable":true,"ispre":false,"isrequired":false,"isreadonly":false,"isonly":false,"bk_issystem":false,"bk_isapi":false,"bk_property_type":"bool","option":false,"description":"","creator":"user","create_time":{"$date":"2023-02-27T03:43:36.299Z"},"last_time":{"$date":"2023-02-27T03:43:36.299Z"},"bk_biz_id":0}
{"_id":{"$oid":"63fc26e898cb185b745d543f"},"id":330,"bk_supplier_account":"0","bk_obj_id":"cmdb_host","bk_property_id":"ClusterName","bk_property_name":"集群名称","bk_property_group":"default","bk_property_index":30,"unit":"","placeholder":"","editable":true,"ispre":false,"isrequired":false,"isreadonly":false,"isonly":false,"bk_issystem":false,"bk_isapi":false,"bk_property_type":"singlechar","option":null,"description":"","creator":"user","create_time":{"$date":"2023-02-27T03:43:36.299Z"},"last_time":{"$date":"2023-02-27T03:43:36.299Z"},"bk_biz_id":0}
{"_id":{"$oid":"63fc26e898cb185b745d53fa"},"id":203,"bk_supplier_account":"0","bk_obj_id":"zone","bk_property_id":"ZonePublicity","bk_property_name":"可用区属性","bk_property_group":"default","bk_property_index":13,"unit":"","placeholder":"","editable":true,"ispre":false,"isrequired":false,"isreadonly":false,"isonly":false,"bk_issystem":false,"bk_isapi":false,"bk_property_type":"bool","option":false,"description":"","creator":"user","create_time":{"$date":"2023-02-27T03:43:36.299Z"},"last_time":{"$date":"2023-02-27T03:43:36.299Z"},"bk_biz_id":0}
{"_id":{"$oid":"63fc26e898cb185b745d541b"},"id":274,"bk_supplier_account":"0","bk_obj_id":"storageBackend","bk_property_id":"IscsiType","bk_property_name":"iscsi类型","bk_property_group":"default","bk_property_index":4,"unit":"","placeholder":"","editable":true,"ispre":false,"isrequired":false,"isreadonly":false,"isonly":false,"bk_issystem":false,"bk_isapi":false,"bk_property_type":"singlechar","option":null,"description":"","creator":"user","create_time":{"$date":"2023-02-27T03:43:36.299Z"},"last_time":{"$date":"2023-02-27T03:43:36.299Z"},"bk_biz_id":0}
{"_id":{"$oid":"6412c5d11e7112c8209617af"},"bk_biz_id":0,"id":331,"bk_supplier_account":"0","bk_obj_id":"cmdb_host","bk_property_id":"Deleted","bk_property_name":"删除标记","bk_property_group":"default","bk_property_index":31,"unit":"","placeholder":"","editable":true,"ispre":false,"isrequired":false,"isreadonly":false,"isonly":false,"bk_issystem":false,"bk_isapi":false,"bk_property_type":"bool","option":false,"description":"","creator":"admin","create_time":{"$date":"2023-03-16T07:31:29.782Z"},"last_time":{"$date":"2023-03-16T07:31:29.782Z"}}
{"_id":{"$oid":"641821f51e7112c82096180f"},"bk_biz_id":0,"id":332,"bk_supplier_account":"0","bk_obj_id":"cluster","bk_property_id":"HostNumber","bk_property_name":"主机数量","bk_property_group":"default","bk_property_index":19,"unit":"","placeholder":"","editable":true,"ispre":false,"isrequired":false,"isreadonly":false,"isonly":false,"bk_issystem":false,"bk_isapi":false,"bk_property_type":"int","option":{"max":"","min":""},"description":"","creator":"admin","create_time":{"$date":"2023-03-20T09:05:57.309Z"},"last_time":{"$date":"2023-03-20T09:05:57.309Z"}}
{"_id":{"$oid":"642e610710e5cccf11973bc0"},"bk_biz_id":0,"id":333,"bk_supplier_account":"0","bk_obj_id":"cmdb_host","bk_property_id":"MetaID","bk_property_name":"MetaDB主机ID","bk_property_group":"default","bk_property_index":32,"unit":"","placeholder":"","editable":true,"ispre":false,"isrequired":false,"isreadonly":false,"isonly":false,"bk_issystem":false,"bk_isapi":false,"bk_property_type":"singlechar","option":"","description":"","creator":"admin","create_time":{"$date":"2023-04-06T06:04:55.106Z"},"last_time":{"$date":"2023-04-06T06:04:55.106Z"}}
{"_id":{"$oid":"642e835710e5cccf11973bd6"},"bk_biz_id":0,"id":334,"bk_supplier_account":"0","bk_obj_id":"cmdb_host","bk_property_id":"ReservedGpu","bk_property_name":"保留gpu资源","bk_property_group":"default","bk_property_index":33,"unit":"","placeholder":"","editable":true,"ispre":false,"isrequired":false,"isreadonly":false,"isonly":false,"bk_issystem":false,"bk_isapi":false,"bk_property_type":"int","option":{"max":"","min":""},"description":"","creator":"admin","create_time":{"$date":"2023-04-06T08:31:19.857Z"},"last_time":{"$date":"2023-04-06T08:31:19.857Z"}}
{"_id":{"$oid":"642e836710e5cccf11973bd8"},"bk_biz_id":0,"id":335,"bk_supplier_account":"0","bk_obj_id":"cmdb_host","bk_property_id":"ReservedGpuMemory","bk_property_name":"保留显存资源","bk_property_group":"default","bk_property_index":34,"unit":"","placeholder":"","editable":true,"ispre":false,"isrequired":false,"isreadonly":false,"isonly":false,"bk_issystem":false,"bk_isapi":false,"bk_property_type":"int","option":{"max":"","min":""},"description":"","creator":"admin","create_time":{"$date":"2023-04-06T08:31:35.498Z"},"last_time":{"$date":"2023-04-06T08:31:35.498Z"}}
{"_id":{"$oid":"642e837510e5cccf11973bda"},"bk_biz_id":0,"id":336,"bk_supplier_account":"0","bk_obj_id":"cmdb_host","bk_property_id":"GpuRatio","bk_property_name":"Gpu超分比","bk_property_group":"default","bk_property_index":35,"unit":"","placeholder":"","editable":true,"ispre":false,"isrequired":false,"isreadonly":false,"isonly":false,"bk_issystem":false,"bk_isapi":false,"bk_property_type":"float","option":{"max":"","min":""},"description":"","creator":"admin","create_time":{"$date":"2023-04-06T08:31:49.112Z"},"last_time":{"$date":"2023-04-06T08:31:49.112Z"}}
{"_id":{"$oid":"642e838210e5cccf11973bdc"},"bk_biz_id":0,"id":337,"bk_supplier_account":"0","bk_obj_id":"cmdb_host","bk_property_id":"GpuMemoryRatio","bk_property_name":"显存超分比","bk_property_group":"default","bk_property_index":36,"unit":"","placeholder":"","editable":true,"ispre":false,"isrequired":false,"isreadonly":false,"isonly":false,"bk_issystem":false,"bk_isapi":false,"bk_property_type":"float","option":{"max":"","min":""},"description":"","creator":"admin","create_time":{"$date":"2023-04-06T08:32:02.555Z"},"last_time":{"$date":"2023-04-06T08:32:02.555Z"}}
{"_id":{"$oid":"642e839c10e5cccf11973bde"},"bk_biz_id":0,"id":338,"bk_supplier_account":"0","bk_obj_id":"cmdb_host","bk_property_id":"TotalGpu","bk_property_name":"TotalGpu","bk_property_group":"default","bk_property_index":37,"unit":"","placeholder":"","editable":true,"ispre":false,"isrequired":false,"isreadonly":false,"isonly":false,"bk_issystem":false,"bk_isapi":false,"bk_property_type":"int","option":{"max":"","min":""},"description":"","creator":"admin","create_time":{"$date":"2023-04-06T08:32:28.083Z"},"last_time":{"$date":"2023-04-06T08:32:28.083Z"}}
{"_id":{"$oid":"642e83a510e5cccf11973be0"},"bk_biz_id":0,"id":339,"bk_supplier_account":"0","bk_obj_id":"cmdb_host","bk_property_id":"TotalGpuMemory","bk_property_name":"TotalGpuMemory","bk_property_group":"default","bk_property_index":38,"unit":"","placeholder":"","editable":true,"ispre":false,"isrequired":false,"isreadonly":false,"isonly":false,"bk_issystem":false,"bk_isapi":false,"bk_property_type":"int","option":{"min":"","max":""},"description":"","creator":"admin","create_time":{"$date":"2023-04-06T08:32:37.322Z"},"last_time":{"$date":"2023-04-06T08:32:37.322Z"}}
{"_id":{"$oid":"642e83b510e5cccf11973be2"},"bk_biz_id":0,"id":340,"bk_supplier_account":"0","bk_obj_id":"cmdb_host","bk_property_id":"CpuModel","bk_property_name":"Cpu型号","bk_property_group":"default","bk_property_index":39,"unit":"","placeholder":"","editable":true,"ispre":false,"isrequired":false,"isreadonly":false,"isonly":false,"bk_issystem":false,"bk_isapi":false,"bk_property_type":"singlechar","option":"","description":"","creator":"admin","create_time":{"$date":"2023-04-06T08:32:53.933Z"},"last_time":{"$date":"2023-04-06T08:32:53.933Z"}}
{"_id":{"$oid":"642e83c110e5cccf11973be4"},"bk_biz_id":0,"id":341,"bk_supplier_account":"0","bk_obj_id":"cmdb_host","bk_property_id":"GpuModel","bk_property_name":"Gpu型号","bk_property_group":"default","bk_property_index":40,"unit":"","placeholder":"","editable":true,"ispre":false,"isrequired":false,"isreadonly":false,"isonly":false,"bk_issystem":false,"bk_isapi":false,"bk_property_type":"singlechar","option":"","description":"","creator":"admin","create_time":{"$date":"2023-04-06T08:33:05.026Z"},"last_time":{"$date":"2023-04-06T08:33:05.026Z"}}
{"_id":{"$oid":"642e83d110e5cccf11973be6"},"bk_biz_id":0,"id":342,"bk_supplier_account":"0","bk_obj_id":"cmdb_host","bk_property_id":"Created","bk_property_name":"是否纳管主机","bk_property_group":"default","bk_property_index":41,"unit":"","placeholder":"","editable":true,"ispre":false,"isrequired":false,"isreadonly":false,"isonly":false,"bk_issystem":false,"bk_isapi":false,"bk_property_type":"bool","option":false,"description":"","creator":"admin","create_time":{"$date":"2023-04-06T08:33:21.409Z"},"last_time":{"$date":"2023-04-06T08:33:21.409Z"}}
{"_id":{"$oid":"6433afa524310b5fe2c77af9"},"bk_biz_id":0,"id":343,"bk_supplier_account":"0","bk_obj_id":"storageBackend","bk_property_id":"RegionID","bk_property_name":"地域ID","bk_property_group":"default","bk_property_index":10,"unit":"","placeholder":"","editable":true,"ispre":false,"isrequired":false,"isreadonly":false,"isonly":false,"bk_issystem":false,"bk_isapi":false,"bk_property_type":"singlechar","option":"","description":"","creator":"admin","create_time":{"$date":"2023-04-10T06:41:41.318Z"},"last_time":{"$date":"2023-04-10T06:43:03.708Z"}}
{"_id":{"$oid":"6433afca24310b5fe2c77afb"},"bk_biz_id":0,"id":344,"bk_supplier_account":"0","bk_obj_id":"storageBackend","bk_property_id":"RegionName","bk_property_name":"地域名称","bk_property_group":"default","bk_property_index":11,"unit":"","placeholder":"","editable":true,"ispre":false,"isrequired":false,"isreadonly":false,"isonly":false,"bk_issystem":false,"bk_isapi":false,"bk_property_type":"singlechar","option":"","description":"","creator":"admin","create_time":{"$date":"2023-04-10T06:42:18.225Z"},"last_time":{"$date":"2023-04-10T06:42:18.225Z"}}
{"_id":{"$oid":"6433afdd24310b5fe2c77afd"},"bk_biz_id":0,"id":345,"bk_supplier_account":"0","bk_obj_id":"storageBackend","bk_property_id":"ZoneID","bk_property_name":"可用区ID","bk_property_group":"default","bk_property_index":12,"unit":"","placeholder":"","editable":true,"ispre":false,"isrequired":false,"isreadonly":false,"isonly":false,"bk_issystem":false,"bk_isapi":false,"bk_property_type":"singlechar","option":"","description":"","creator":"admin","create_time":{"$date":"2023-04-10T06:42:37.575Z"},"last_time":{"$date":"2023-04-10T06:42:37.575Z"}}
{"_id":{"$oid":"6433afec24310b5fe2c77aff"},"bk_biz_id":0,"id":346,"bk_supplier_account":"0","bk_obj_id":"storageBackend","bk_property_id":"ZoneName","bk_property_name":"可用区名称","bk_property_group":"default","bk_property_index":13,"unit":"","placeholder":"","editable":true,"ispre":false,"isrequired":false,"isreadonly":false,"isonly":false,"bk_issystem":false,"bk_isapi":false,"bk_property_type":"singlechar","option":"","description":"","creator":"admin","create_time":{"$date":"2023-04-10T06:42:52.373Z"},"last_time":{"$date":"2023-04-10T06:43:33.562Z"}}
{"_id":{"$oid":"6433b00c24310b5fe2c77b02"},"bk_biz_id":0,"id":347,"bk_supplier_account":"0","bk_obj_id":"storageBackend","bk_property_id":"Deleted","bk_property_name":"删除标记","bk_property_group":"default","bk_property_index":14,"unit":"","placeholder":"","editable":true,"ispre":false,"isrequired":false,"isreadonly":false,"isonly":false,"bk_issystem":false,"bk_isapi":false,"bk_property_type":"bool","option":false,"description":"","creator":"admin","create_time":{"$date":"2023-04-10T06:43:24.9Z"},"last_time":{"$date":"2023-04-10T06:43:24.9Z"}}
{"_id":{"$oid":"6433b03e24310b5fe2c77b05"},"bk_biz_id":0,"id":348,"bk_supplier_account":"0","bk_obj_id":"storageBackendPool","bk_property_id":"Deleted","bk_property_name":"删除标记","bk_property_group":"default","bk_property_index":7,"unit":"","placeholder":"","editable":true,"ispre":false,"isrequired":false,"isreadonly":false,"isonly":false,"bk_issystem":false,"bk_isapi":false,"bk_property_type":"bool","option":false,"description":"","creator":"admin","create_time":{"$date":"2023-04-10T06:44:14.816Z"},"last_time":{"$date":"2023-04-10T06:44:14.816Z"}}
{"_id":{"$oid":"6437621def2d1e20404a7fad"},"bk_biz_id":0,"id":349,"bk_supplier_account":"0","bk_obj_id":"region","bk_property_id":"StackIP","bk_property_name":"StackIP","bk_property_group":"default","bk_property_index":12,"unit":"","placeholder":"","editable":true,"ispre":false,"isrequired":false,"isreadonly":false,"isonly":false,"bk_issystem":false,"bk_isapi":false,"bk_property_type":"singlechar","option":"","description":"","creator":"admin","create_time":{"$date":"2023-04-13T01:59:57.236Z"},"last_time":{"$date":"2023-04-13T01:59:57.236Z"}}
{"_id":{"$oid":"64376236ef2d1e20404a7fb1"},"bk_biz_id":0,"id":351,"bk_supplier_account":"0","bk_obj_id":"region","bk_property_id":"StackControllerURL","bk_property_name":"StackControllerURL","bk_property_group":"default","bk_property_index":14,"unit":"","placeholder":"","editable":true,"ispre":false,"isrequired":false,"isreadonly":false,"isonly":false,"bk_issystem":false,"bk_isapi":false,"bk_property_type":"singlechar","option":"","description":"","creator":"admin","create_time":{"$date":"2023-04-13T02:00:22.32Z"},"last_time":{"$date":"2023-04-13T02:00:22.32Z"}}
{"_id":{"$oid":"64376240ef2d1e20404a7fb3"},"bk_biz_id":0,"id":352,"bk_supplier_account":"0","bk_obj_id":"region","bk_property_id":"StackControllerEventURL","bk_property_name":"StackControllerEventURL","bk_property_group":"default","bk_property_index":15,"unit":"","placeholder":"","editable":true,"ispre":false,"isrequired":false,"isreadonly":false,"isonly":false,"bk_issystem":false,"bk_isapi":false,"bk_property_type":"singlechar","option":"","description":"","creator":"admin","create_time":{"$date":"2023-04-13T02:00:32.396Z"},"last_time":{"$date":"2023-04-13T02:00:32.396Z"}}
{"_id":{"$oid":"64376248ef2d1e20404a7fb5"},"bk_biz_id":0,"id":353,"bk_supplier_account":"0","bk_obj_id":"region","bk_property_id":"NetworkControllerURL","bk_property_name":"NetworkControllerURL","bk_property_group":"default","bk_property_index":16,"unit":"","placeholder":"","editable":true,"ispre":false,"isrequired":false,"isreadonly":false,"isonly":false,"bk_issystem":false,"bk_isapi":false,"bk_property_type":"singlechar","option":"","description":"","creator":"admin","create_time":{"$date":"2023-04-13T02:00:40.035Z"},"last_time":{"$date":"2023-04-13T02:00:40.035Z"}}
{"_id":{"$oid":"6437628cef2d1e20404a7fb7"},"bk_biz_id":0,"id":354,"bk_supplier_account":"0","bk_obj_id":"cmdb_host","bk_property_id":"SSHIp","bk_property_name":"SSHIp","bk_property_group":"default","bk_property_index":42,"unit":"","placeholder":"","editable":true,"ispre":false,"isrequired":false,"isreadonly":false,"isonly":false,"bk_issystem":false,"bk_isapi":false,"bk_property_type":"singlechar","option":"","description":"","creator":"admin","create_time":{"$date":"2023-04-13T02:01:48.758Z"},"last_time":{"$date":"2023-04-13T02:01:48.758Z"}}
{"_id":{"$oid":"6437629aef2d1e20404a7fb9"},"bk_biz_id":0,"id":355,"bk_supplier_account":"0","bk_obj_id":"cmdb_host","bk_property_id":"SSHUsername","bk_property_name":"SSH用户名","bk_property_group":"default","bk_property_index":43,"unit":"","placeholder":"","editable":true,"ispre":false,"isrequired":false,"isreadonly":false,"isonly":false,"bk_issystem":false,"bk_isapi":false,"bk_property_type":"singlechar","option":"","description":"","creator":"admin","create_time":{"$date":"2023-04-13T02:02:02.238Z"},"last_time":{"$date":"2023-04-13T02:02:02.238Z"}}
{"_id":{"$oid":"643762afef2d1e20404a7fbb"},"bk_biz_id":0,"id":356,"bk_supplier_account":"0","bk_obj_id":"cmdb_host","bk_property_id":"SSHPassword","bk_property_name":"SSH密码","bk_property_group":"default","bk_property_index":44,"unit":"","placeholder":"","editable":true,"ispre":false,"isrequired":false,"isreadonly":false,"isonly":false,"bk_issystem":false,"bk_isapi":false,"bk_property_type":"singlechar","option":"","description":"","creator":"admin","create_time":{"$date":"2023-04-13T02:02:23.175Z"},"last_time":{"$date":"2023-04-13T02:02:23.175Z"}}
{"_id":{"$oid":"643762bbef2d1e20404a7fbd"},"bk_biz_id":0,"id":357,"bk_supplier_account":"0","bk_obj_id":"cmdb_host","bk_property_id":"SSHPort","bk_property_name":"SSH端口","bk_property_group":"default","bk_property_index":45,"unit":"","placeholder":"","editable":true,"ispre":false,"isrequired":false,"isreadonly":false,"isonly":false,"bk_issystem":false,"bk_isapi":false,"bk_property_type":"singlechar","option":"","description":"","creator":"admin","create_time":{"$date":"2023-04-13T02:02:35.704Z"},"last_time":{"$date":"2023-04-13T02:02:35.704Z"}}
{"_id":{"$oid":"6437cb78ef2d1e20404a8000"},"bk_biz_id":0,"id":359,"bk_supplier_account":"0","bk_obj_id":"cmdb_host","bk_property_id":"HostTag","bk_property_name":"HostTag","bk_property_group":"default","bk_property_index":47,"unit":"","placeholder":"","editable":true,"ispre":false,"isrequired":false,"isreadonly":false,"isonly":false,"bk_issystem":false,"bk_isapi":false,"bk_property_type":"singlechar","option":"","description":"","creator":"admin","create_time":{"$date":"2023-04-13T09:29:28.194Z"},"last_time":{"$date":"2023-04-13T09:29:28.194Z"}}
{"_id":{"$oid":"6437cda4ef2d1e20404a8003"},"bk_biz_id":0,"id":360,"bk_supplier_account":"0","bk_obj_id":"cmdb_host","bk_property_id":"HostArchitecture","bk_property_name":"HostArchitecture","bk_property_group":"default","bk_property_index":48,"unit":"","placeholder":"","editable":true,"ispre":false,"isrequired":false,"isreadonly":false,"isonly":false,"bk_issystem":false,"bk_isapi":false,"bk_property_type":"singlechar","option":"","description":"","creator":"admin","create_time":{"$date":"2023-04-13T09:38:44.267Z"},"last_time":{"$date":"2023-04-13T09:38:44.267Z"}}
{"_id":{"$oid":"6437e4a6ef2d1e20404a8005"},"bk_biz_id":0,"id":361,"bk_supplier_account":"0","bk_obj_id":"region","bk_property_id":"CargoURL","bk_property_name":"下发URL","bk_property_group":"default","bk_property_index":17,"unit":"","placeholder":"","editable":true,"ispre":false,"isrequired":false,"isreadonly":false,"isonly":false,"bk_issystem":false,"bk_isapi":false,"bk_property_type":"singlechar","option":"","description":"","creator":"admin","create_time":{"$date":"2023-04-13T11:16:54.543Z"},"last_time":{"$date":"2023-04-13T11:16:54.543Z"}}
{"_id":{"$oid":"6437e4b0ef2d1e20404a8007"},"bk_biz_id":0,"id":362,"bk_supplier_account":"0","bk_obj_id":"region","bk_property_id":"CombineURL","bk_property_name":"采集URL","bk_property_group":"default","bk_property_index":18,"unit":"","placeholder":"","editable":true,"ispre":false,"isrequired":false,"isreadonly":false,"isonly":false,"bk_issystem":false,"bk_isapi":false,"bk_property_type":"singlechar","option":"","description":"","creator":"admin","create_time":{"$date":"2023-04-13T11:17:04.953Z"},"last_time":{"$date":"2023-04-13T11:17:04.953Z"}}
{"_id":{"$oid":"6437e77cef2d1e20404a800a"},"bk_biz_id":0,"id":363,"bk_supplier_account":"0","bk_obj_id":"region","bk_property_id":"StackPort","bk_property_name":"Stack端口","bk_property_group":"default","bk_property_index":19,"unit":"","placeholder":"","editable":true,"ispre":false,"isrequired":false,"isreadonly":false,"isonly":false,"bk_issystem":false,"bk_isapi":false,"bk_property_type":"int","option":{"max":"","min":""},"description":"","creator":"admin","create_time":{"$date":"2023-04-13T11:29:00.787Z"},"last_time":{"$date":"2023-04-13T11:29:00.787Z"}}
{"_id":{"$oid":"643d419eef2d1e20404a8122"},"bk_biz_id":0,"id":364,"bk_supplier_account":"0","bk_obj_id":"region","bk_property_id":"Rules","bk_property_name":"地域规则","bk_property_group":"default","bk_property_index":20,"unit":"","placeholder":"","editable":true,"ispre":false,"isrequired":false,"isreadonly":false,"isonly":false,"bk_issystem":false,"bk_isapi":false,"bk_property_type":"longchar","option":"","description":"","creator":"admin","create_time":{"$date":"2023-04-17T12:54:54.544Z"},"last_time":{"$date":"2023-04-17T12:54:54.544Z"}}
{"_id":{"$oid":"643d41c1ef2d1e20404a8126"},"bk_biz_id":0,"id":365,"bk_supplier_account":"0","bk_obj_id":"cluster","bk_property_id":"TagIDs","bk_property_name":"TagIDs","bk_property_group":"default","bk_property_index":20,"unit":"","placeholder":"","editable":true,"ispre":false,"isrequired":false,"isreadonly":false,"isonly":false,"bk_issystem":false,"bk_isapi":false,"bk_property_type":"longchar","option":"","description":"","creator":"admin","create_time":{"$date":"2023-04-17T12:55:29.976Z"},"last_time":{"$date":"2023-04-17T12:55:29.976Z"}}
{"_id":{"$oid":"643d41ceef2d1e20404a8128"},"bk_biz_id":0,"id":366,"bk_supplier_account":"0","bk_obj_id":"cluster","bk_property_id":"Tags","bk_property_name":"Tags","bk_property_group":"default","bk_property_index":21,"unit":"","placeholder":"","editable":true,"ispre":false,"isrequired":false,"isreadonly":false,"isonly":false,"bk_issystem":false,"bk_isapi":false,"bk_property_type":"longchar","option":"","description":"","creator":"admin","create_time":{"$date":"2023-04-17T12:55:42.221Z"},"last_time":{"$date":"2023-04-17T12:55:42.221Z"}}
{"_id":{"$oid":"643e4cfdef2d1e20404a8182"},"bk_biz_id":0,"id":367,"bk_supplier_account":"0","bk_obj_id":"storageBackend","bk_property_id":"StorageBackendName","bk_property_name":"存储后端名称","bk_property_group":"default","bk_property_index":15,"unit":"","placeholder":"","editable":true,"ispre":false,"isrequired":false,"isreadonly":false,"isonly":false,"bk_issystem":false,"bk_isapi":false,"bk_property_type":"singlechar","option":"","description":"","creator":"admin","create_time":{"$date":"2023-04-18T07:55:41.548Z"},"last_time":{"$date":"2023-04-18T07:55:41.548Z"}}
{"_id":{"$oid":"643fe20aef2d1e20404a824c"},"bk_biz_id":0,"id":368,"bk_supplier_account":"0","bk_obj_id":"storageBackend","bk_property_id":"MountStorageIP","bk_property_name":"存储挂载IP","bk_property_group":"default","bk_property_index":16,"unit":"","placeholder":"","editable":true,"ispre":false,"isrequired":false,"isreadonly":false,"isonly":false,"bk_issystem":false,"bk_isapi":false,"bk_property_type":"singlechar","option":"","description":"","creator":"admin","create_time":{"$date":"2023-04-19T12:43:54.242Z"},"last_time":{"$date":"2023-04-19T12:43:54.242Z"}}
{"_id":{"$oid":"643fe23bef2d1e20404a824e"},"bk_biz_id":0,"id":369,"bk_supplier_account":"0","bk_obj_id":"storageBackend","bk_property_id":"MountStoragePort","bk_property_name":"存储挂载端口","bk_property_group":"default","bk_property_index":17,"unit":"","placeholder":"","editable":true,"ispre":false,"isrequired":false,"isreadonly":false,"isonly":false,"bk_issystem":false,"bk_isapi":false,"bk_property_type":"singlechar","option":"","description":"","creator":"admin","create_time":{"$date":"2023-04-19T12:44:43.865Z"},"last_time":{"$date":"2023-04-19T12:44:43.865Z"}}
{"_id":{"$oid":"643fe254ef2d1e20404a8250"},"bk_biz_id":0,"id":370,"bk_supplier_account":"0","bk_obj_id":"storageBackend","bk_property_id":"MountStorageUser","bk_property_name":"存储挂载的用户名","bk_property_group":"default","bk_property_index":18,"unit":"","placeholder":"","editable":true,"ispre":false,"isrequired":false,"isreadonly":false,"isonly":false,"bk_issystem":false,"bk_isapi":false,"bk_property_type":"singlechar","option":"","description":"","creator":"admin","create_time":{"$date":"2023-04-19T12:45:08.949Z"},"last_time":{"$date":"2023-04-19T12:45:08.949Z"}}
{"_id":{"$oid":"643fe262ef2d1e20404a8252"},"bk_biz_id":0,"id":371,"bk_supplier_account":"0","bk_obj_id":"storageBackend","bk_property_id":"MountStoragePass","bk_property_name":"存储挂载的密码","bk_property_group":"default","bk_property_index":19,"unit":"","placeholder":"","editable":true,"ispre":false,"isrequired":false,"isreadonly":false,"isonly":false,"bk_issystem":false,"bk_isapi":false,"bk_property_type":"singlechar","option":"","description":"","creator":"admin","create_time":{"$date":"2023-04-19T12:45:22.945Z"},"last_time":{"$date":"2023-04-19T12:45:22.945Z"}}
{"_id":{"$oid":"643fe2eaef2d1e20404a8254"},"bk_biz_id":0,"id":372,"bk_supplier_account":"0","bk_obj_id":"storageBackend","bk_property_id":"IscsiPath","bk_property_name":"iscsi路径","bk_property_group":"default","bk_property_index":20,"unit":"","placeholder":"","editable":true,"ispre":false,"isrequired":false,"isreadonly":false,"isonly":false,"bk_issystem":false,"bk_isapi":false,"bk_property_type":"singlechar","option":"","description":"","creator":"admin","create_time":{"$date":"2023-04-19T12:47:38.97Z"},"last_time":{"$date":"2023-04-19T12:47:38.97Z"}}
{"_id":{"$oid":"6440f2a4ad97789fada7cf34"},"bk_biz_id":0,"id":373,"bk_supplier_account":"0","bk_obj_id":"storageBackend","bk_property_id":"ConfigUrl","bk_property_name":"配置URL","bk_property_group":"default","bk_property_index":21,"unit":"","placeholder":"","editable":true,"ispre":false,"isrequired":false,"isreadonly":false,"isonly":false,"bk_issystem":false,"bk_isapi":false,"bk_property_type":"singlechar","option":"","description":"","creator":"admin","create_time":{"$date":"2023-04-20T08:07:00.493Z"},"last_time":{"$date":"2023-04-20T08:07:00.493Z"}}
{"_id":{"$oid":"6440f2aead97789fada7cf36"},"bk_biz_id":0,"id":374,"bk_supplier_account":"0","bk_obj_id":"storageBackend","bk_property_id":"ConfigUsername","bk_property_name":"配置用户名","bk_property_group":"default","bk_property_index":22,"unit":"","placeholder":"","editable":true,"ispre":false,"isrequired":false,"isreadonly":false,"isonly":false,"bk_issystem":false,"bk_isapi":false,"bk_property_type":"singlechar","option":"","description":"","creator":"admin","create_time":{"$date":"2023-04-20T08:07:10.732Z"},"last_time":{"$date":"2023-04-20T08:07:10.732Z"}}
{"_id":{"$oid":"6440f2b7ad97789fada7cf38"},"bk_biz_id":0,"id":375,"bk_supplier_account":"0","bk_obj_id":"storageBackend","bk_property_id":"ConfigPassword","bk_property_name":"配置密码","bk_property_group":"default","bk_property_index":23,"unit":"","placeholder":"","editable":true,"ispre":false,"isrequired":false,"isreadonly":false,"isonly":false,"bk_issystem":false,"bk_isapi":false,"bk_property_type":"singlechar","option":"","description":"","creator":"admin","create_time":{"$date":"2023-04-20T08:07:19.224Z"},"last_time":{"$date":"2023-04-20T08:07:19.224Z"}}
{"_id":{"$oid":"644235c2ad97789fada7cf44"},"bk_biz_id":0,"id":379,"bk_supplier_account":"0","bk_obj_id":"cmdb_host","bk_property_id":"ManagementInfo","bk_property_name":"纳管状态信息","bk_property_group":"default","bk_property_index":50,"unit":"","placeholder":"","editable":true,"ispre":false,"isrequired":false,"isreadonly":false,"isonly":false,"bk_issystem":false,"bk_isapi":false,"bk_property_type":"longchar","option":"","description":"","creator":"admin","create_time":{"$date":"2023-04-21T07:05:38.15Z"},"last_time":{"$date":"2023-04-21T07:05:38.15Z"}}
{"_id":{"$oid":"64426c95ad97789fada7cfc9"},"bk_biz_id":0,"id":380,"bk_supplier_account":"0","bk_obj_id":"cmdb_host","bk_property_id":"ManagementState","bk_property_name":"纳管状态","bk_property_group":"default","bk_property_index":51,"unit":"","placeholder":"","editable":true,"ispre":false,"isrequired":false,"isreadonly":false,"isonly":false,"bk_issystem":false,"bk_isapi":false,"bk_property_type":"singlechar","option":"","description":"","creator":"admin","create_time":{"$date":"2023-04-21T10:59:33.267Z"},"last_time":{"$date":"2023-04-21T10:59:33.267Z"}}
